beam_nuggets/__init__.py
beam_nuggets/io/__init__.py
beam_nuggets/io/csvio.py
beam_nuggets/io/kafkaio.py
beam_nuggets/io/relational_db.py
beam_nuggets/io/relational_db_api.py
beam_nuggets/io/test/__init__.py
beam_nuggets/io/test/database.py
beam_nuggets/io/test/test_base.py
beam_nuggets/io/test/test_kafkaio.py
beam_nuggets/io/test/test_read_transform.py
beam_nuggets/io/test/test_relational_db_api.py
beam_nuggets/io/test/test_write_transform.py
beam_nuggets/transforms/__init__.py
beam_nuggets/transforms/json_.py
beam_nuggets/transforms/nested_dict.py
beam_nuggets/transforms/unique_id.py
sd_beam_nuggets-0.15.3.dist-info/LICENSE
sd_beam_nuggets-0.15.3.dist-info/METADATA
sd_beam_nuggets-0.15.3.dist-info/WHEEL
sd_beam_nuggets-0.15.3.dist-info/top_level.txt
sd_beam_nuggets-0.15.3.dist-info/RECORD
