Metadata-Version: 2.1
Name: sd-beam-nuggets
Version: 0.15.3
Summary: Collection of transforms for the Apache beam python SDK. Forks the original Mohamed Haseeb repository to make some workarounds
Home-page: https://github.com/rodalgon/beam-nuggets
Author: Rodrigo Gonçalves
Author-email: rodrigoalvs.goncalves@gmail.com
License: UNKNOWN
Platform: UNKNOWN
Classifier: Programming Language :: Python
Classifier: License :: OSI Approved :: MIT License
Classifier: Operating System :: OS Independent
Requires-Dist: apache-beam (<3.0.0,>=2.8.0)
Requires-Dist: SQLAlchemy (<=1.3.15,>=1.3.14)
Requires-Dist: sqlalchemy-utils (<0.34,>=0.33.11)
Requires-Dist: pg8000 (<2.0.0,>=1.12.4)
Requires-Dist: PyMySQL (<2.0.0,>=0.9.3)
Requires-Dist: kafka (>===1.3.5)
Provides-Extra: dev
Requires-Dist: nose (<2.0.0,>=1.3.7) ; extra == 'dev'
Requires-Dist: testing.postgresql (<2.0.0,>=1.3.0) ; extra == 'dev'
Requires-Dist: testing.mysqld (<2.0.0,>=1.4.0) ; extra == 'dev'
Requires-Dist: numpy (<2.0.0,>=1.15.4) ; extra == 'dev'
Requires-Dist: pandas (<0.24,>=0.23.4) ; extra == 'dev'
Requires-Dist: Sphinx (<2.0.0,>=1.8.3) ; extra == 'dev'
Requires-Dist: sphinx-rtd-theme (<2.0.0,>=0.4.2) ; extra == 'dev'
